PyppeteerProtect/PyppeteerProtect.py
PyppeteerProtect-1.0.1.dist-info/LICENSE
PyppeteerProtect-1.0.1.dist-info/METADATA
PyppeteerProtect-1.0.1.dist-info/WHEEL
PyppeteerProtect-1.0.1.dist-info/top_level.txt
PyppeteerProtect-1.0.1.dist-info/RECORD
