Metadata-Version: 2.1
Name: PyppeteerProtect
Version: 1.0.1
Summary: A library to prevent detections caused by Runtime.enable.
Author: packed-re
Project-URL: Homepage, https://github.com/packed-re/PyppeteerProtect
Project-URL: Issues, https://github.com/packed-re/PyppeteerProtect/issues
Classifier: Programming Language :: Python :: 3
Classifier: License :: OSI Approved :: MIT License
Classifier: Operating System :: OS Independent
Requires-Python: >=3.8
License-File: LICENSE
